Workbook

Sheet Inputs
A1: Egypt 3D Print Platform — Assumptions (edit yellow/orange cells)
A3: MACRO
A4: FX rate (EGP per USD) | B4: 49 | C4: Volatile — verify before use
A5: PER-JOB FULFILLMENT COST (owner-borne, not platform)
A6: Avg job weight (g) | B6: 50 | C6: Representative B2B functional part
A7: Material cost (EGP / g) | B7: 1.2 | C7: Local PLA/PETG — validate at purchase
A8: Avg print time (hours) | B8: 4
A9: Printer depreciation (EGP / hr) | B9: 25 | C9: Corrected: ~65-100k printer / 3000 hrs
A10: Electricity (EGP / job) | B10: 4 | C10: Low EG residential tariff
A11: Labor / handling (EGP / job) | B11: 20 | C11: Slice + setup + QC + pack
A12: Packaging (EGP / job) | B12: 15
A13: Failure allowance | B13: 0.12 | C13: Reprint provision — 12%
A14: REVENUE LEVERS
A15: B2B blended AOV (EGP) | B15: 1200 | C15: KEY UNKNOWN — measure from order 1
A16: Platform take rate | B16: 0.2 | C16: Commission on GMV
A17: Design attach rate | B17: 0.2 | C17: Share of orders that add design/CAD service
A18: Design margin (EGP / attached job) | B18: 800 | C18: CAD repair / design-to-print — high margin
A19: PSP fee on collected | B19: 0.025 | C19: Paymob blended; 0 for COD/InstaPay
A20: Bosta shipping (EGP / order) | B20: 40 | C20: ~15 EGP at 50+ orders/mo; add to quote or absorb
A21: MONTHLY OVERHEAD
A22: Fixed monthly overhead (EGP) | B22: 15000 | C22: Tools, WhatsApp API, hosting, misc
A23: Founder draw (EGP) | B23: 0 | C23: Set > 0 to test livable-wage break-even
A25: Legend:
A26: Yellow = editable assumption
A27: Orange = needs local field validation
A28: Green = calculated (do not edit)

Sheet Unit Economics
A1: Per-Order Unit Economics
A3: OWNER-BORNE FULFILLMENT COST (what printer owner spends per job)
A4: Material | B4: =Inputs!$B$6*Inputs!$B$7
A5: Depreciation | B5: =Inputs!$B$8*Inputs!$B$9
A6: Electricity | B6: =Inputs!$B$10
A7: Labor / handling | B7: =Inputs!$B$11
A8: Packaging | B8: =Inputs!$B$12
A9: Subtotal (pre-failure) | B9: =SUM('Unit Economics'!B4:B8)
A10: Failure allowance | B10: ='Unit Economics'!B9*Inputs!$B$13
A11: TOTAL FULFILLMENT COST | B11: ='Unit Economics'!B9+'Unit Economics'!B10
A12: PLATFORM ECONOMICS (what the platform earns per order)
A13: Order AOV | B13: =Inputs!$B$15
A14: Platform commission | B14: ='Unit Economics'!B13*Inputs!$B$16
A15: minus PSP fee | B15: =-'Unit Economics'!B13*Inputs!$B$19
A16: Net margin — print only | B16: ='Unit Economics'!B14+'Unit Economics'!B15
A17: Owner net (AOV - commission - fulfillment) | B17: ='Unit Economics'!B13-'Unit Economics'!B14-'Unit Economics'!B11
A18: DESIGN SERVICE ADD-ON (when attached)
A19: Design margin / attached job | B19: =Inputs!$B$18
A20: Blended margin / order (print + attach*design) | B20: ='Unit Economics'!B16+(Inputs!$B$17*'Unit Economics'!B19)
A21: This blended figure is what feeds the Monthly Model break-even.

Sheet Monthly Model
A1: Monthly P&L — Conservative / Base / Optimistic
A3: Line | B3: Conservative | C3: Base | D3: Optimistic
A4: Print orders / month | B4: 40 | C4: 80 | D4: 150
A5: AOV override (EGP) | B5: 900 | C5: 1200 | D5: 1800
A6: Print GMV | B6: =B4*B5 | C6: =C4*C5 | D6: =D4*D5
A7: Platform commission (take-rate on GMV) | B7: =B6*Inputs!$B$16 | C7: =C6*Inputs!$B$16 | D7: =D6*Inputs!$B$16
A8: minus PSP fees | B8: =-B6*Inputs!$B$19 | C8: =-C6*Inputs!$B$19 | D8: =-D6*Inputs!$B$19
A9: Design revenue | B9: =B4*Inputs!$B$17*Inputs!$B$18 | C9: =C4*Inputs!$B$17*Inputs!$B$18 | D9: =D4*Inputs!$B$17*Inputs!$B$18
A10: GROSS CONTRIBUTION | B10: =B7+B8+B9 | C10: =C7+C8+C9 | D10: =D7+D8+D9
A11: Fixed overhead | B11: =-Inputs!$B$22 | C11: =-Inputs!$B$22 | D11: =-Inputs!$B$22
A12: Founder draw | B12: =-Inputs!$B$23 | C12: =-Inputs!$B$23 | D12: =-Inputs!$B$23
A13: NET PROFIT / MONTH (EGP) | B13: =B10+B11+B12 | C13: =C10+C11+C12 | D13: =D10+D11+D12
A14: NET PROFIT / MONTH (USD) | B14: =B13/Inputs!$B$4 | C14: =C13/Inputs!$B$4 | D14: =D13/Inputs!$B$4
A15: Annualized net (EGP) | B15: =B13*12 | C15: =C13*12 | D15: =D13*12

Sheet Break-even
A1: Break-even & Sensitivity Grid
A3: Blended margin / order (from Unit Economics) | B3: ='Unit Economics'!$B$20
A4: Monthly fixed costs (overhead + draw) | B4: =Inputs!$B$22+Inputs!$B$23
A5: BREAK-EVEN orders / month | B5: =B4/B3
A6: Break-even orders / day (26 working days) | B6: =B5/26
A8: Sensitivity: break-even orders/month
A9: AOV \ Take-rate → | B9: 0.15 | C9: 0.2 | D9: 0.25 | E9: 0.3
A10: 600 | B10: =(Inputs!$B$22+Inputs!$B$23)/((600*0.15)-(600*Inputs!$B$19)+(Inputs!$B$17*Inputs!$B$18)) | C10: =(Inputs!$B$22+Inputs!$B$23)/((600*0.2)-(600*Inputs!$B$19)+(Inputs!$B$17*Inputs!$B$18)) | D10: =(Inputs!$B$22+Inputs!$B$23)/((600*0.25)-(600*Inputs!$B$19)+(Inputs!$B$17*Inputs!$B$18)) | E10: =(Inputs!$B$22+Inputs!$B$23)/((600*0.3)-(600*Inputs!$B$19)+(Inputs!$B$17*Inputs!$B$18))
A11: 900 | B11: =(Inputs!$B$22+Inputs!$B$23)/((900*0.15)-(900*Inputs!$B$19)+(Inputs!$B$17*Inputs!$B$18)) | C11: =(Inputs!$B$22+Inputs!$B$23)/((900*0.2)-(900*Inputs!$B$19)+(Inputs!$B$17*Inputs!$B$18)) | D11: =(Inputs!$B$22+Inputs!$B$23)/((900*0.25)-(900*Inputs!$B$19)+(Inputs!$B$17*Inputs!$B$18)) | E11: =(Inputs!$B$22+Inputs!$B$23)/((900*0.3)-(900*Inputs!$B$19)+(Inputs!$B$17*Inputs!$B$18))
A12: 1200 | B12: =(Inputs!$B$22+Inputs!$B$23)/((1200*0.15)-(1200*Inputs!$B$19)+(Inputs!$B$17*Inputs!$B$18)) | C12: =(Inputs!$B$22+Inputs!$B$23)/((1200*0.2)-(1200*Inputs!$B$19)+(Inputs!$B$17*Inputs!$B$18)) | D12: =(Inputs!$B$22+Inputs!$B$23)/((1200*0.25)-(1200*Inputs!$B$19)+(Inputs!$B$17*Inputs!$B$18)) | E12: =(Inputs!$B$22+Inputs!$B$23)/((1200*0.3)-(1200*Inputs!$B$19)+(Inputs!$B$17*Inputs!$B$18))
A13: 1500 | B13: =(Inputs!$B$22+Inputs!$B$23)/((1500*0.15)-(1500*Inputs!$B$19)+(Inputs!$B$17*Inputs!$B$18)) | C13: =(Inputs!$B$22+Inputs!$B$23)/((1500*0.2)-(1500*Inputs!$B$19)+(Inputs!$B$17*Inputs!$B$18)) | D13: =(Inputs!$B$22+Inputs!$B$23)/((1500*0.25)-(1500*Inputs!$B$19)+(Inputs!$B$17*Inputs!$B$18)) | E13: =(Inputs!$B$22+Inputs!$B$23)/((1500*0.3)-(1500*Inputs!$B$19)+(Inputs!$B$17*Inputs!$B$18))
A14: 2000 | B14: =(Inputs!$B$22+Inputs!$B$23)/((2000*0.15)-(2000*Inputs!$B$19)+(Inputs!$B$17*Inputs!$B$18)) | C14: =(Inputs!$B$22+Inputs!$B$23)/((2000*0.2)-(2000*Inputs!$B$19)+(Inputs!$B$17*Inputs!$B$18)) | D14: =(Inputs!$B$22+Inputs!$B$23)/((2000*0.25)-(2000*Inputs!$B$19)+(Inputs!$B$17*Inputs!$B$18)) | E14: =(Inputs!$B$22+Inputs!$B$23)/((2000*0.3)-(2000*Inputs!$B$19)+(Inputs!$B$17*Inputs!$B$18))
A15: 3000 | B15: =(Inputs!$B$22+Inputs!$B$23)/((3000*0.15)-(3000*Inputs!$B$19)+(Inputs!$B$17*Inputs!$B$18)) | C15: =(Inputs!$B$22+Inputs!$B$23)/((3000*0.2)-(3000*Inputs!$B$19)+(Inputs!$B$17*Inputs!$B$18)) | D15: =(Inputs!$B$22+Inputs!$B$23)/((3000*0.25)-(3000*Inputs!$B$19)+(Inputs!$B$17*Inputs!$B$18)) | E15: =(Inputs!$B$22+Inputs!$B$23)/((3000*0.3)-(3000*Inputs!$B$19)+(Inputs!$B$17*Inputs!$B$18))
A17: Read: number of print orders/month needed to break even at that AOV + take-rate combination.
A18: Design attach rate and margin are pulled from Inputs — change them there to see impact.

Sheet Kill Criteria
A1: Concierge MVP — Kill Criteria Tracker (first 30 orders)
A3: Order # | B3: Date | C3: Segment | D3: AOV (EGP) | E3: Payment Rail | F3: Repeat? (Y/N) | G3: Design attached? | H3: Notes
A4: 1
A5: 2
A6: 3
A7: 4
A8: 5
A9: 6
A10: 7
A11: 8
A12: 9
A13: 10
A14: 11
A15: 12
... A33: 30
A35: SUMMARY
A36: Avg AOV (EGP) | B36: =IFERROR(AVERAGE(D4:D33),"no data")
A37: Repeat rate | B37: =IFERROR(COUNTIF(F4:F33,"Y")/COUNTA(F4:F33),"no data")
A38: Design attach rate | B38: =IFERROR(COUNTIF(G4:G33,"Y")/COUNTA(G4:G33),"no data")
A39: Total orders | B39: =COUNTA(A4:A33)
A41: Kill criteria: Repeat rate >= 30% | AOV >= 800 EGP | Design attach >= 20%
